aioharmony/__init__.py
aioharmony/__main__.py
aioharmony/__version__.py
aioharmony/const.py
aioharmony/exceptions.py
aioharmony/handler.py
aioharmony/harmonyapi.py
aioharmony/harmonyclient.py
aioharmony/helpers.py
aioharmony/hubconnector_websocket.py
aioharmony/hubconnector_xmpp.py
aioharmony/json.py
aioharmony/responsehandler.py
aioharmony-0.5.3.dist-info/licenses/AUTHORS
aioharmony-0.5.3.dist-info/licenses/LICENSE
aioharmony-0.5.3.dist-info/METADATA
aioharmony-0.5.3.dist-info/WHEEL
aioharmony-0.5.3.dist-info/entry_points.txt
aioharmony-0.5.3.dist-info/top_level.txt
aioharmony-0.5.3.dist-info/RECORD
