Metadata-Version: 2.4
Name: aioharmony
Version: 0.5.3
Summary: asyncio Python library for connecting to and controlling the Logitech Harmony
Author-email: Erik Hendrix <endrix_erik@hotmail.com>, "J. Nick Koston" <nick@koston.org>
License: Apache-2.0
Project-URL: Bug Tracker, https://github.com/harmony-libs/aioharmony/issues
Project-URL: Changelog, https://github.com/harmony-libs/aioharmony/blob/main/CHANGELOG.md
Project-URL: repository, https://github.com/harmony-libs/aioharmony
Classifier: Framework :: AsyncIO
Classifier: Intended Audience :: Developers
Classifier: License :: OSI Approved :: Apache Software License
Classifier: Programming Language :: Python
Classifier: Programming Language :: Python :: 3
Classifier: Programming Language :: Python :: 3.9
Classifier: Programming Language :: Python :: 3.10
Classifier: Programming Language :: Python :: 3.11
Classifier: Programming Language :: Python :: 3.12
Classifier: Programming Language :: Python :: 3.13
Classifier: Programming Language :: Python :: Implementation :: CPython
Classifier: Programming Language :: Python :: Implementation :: PyPy
Classifier: Topic :: Home Automation
Classifier: Topic :: Software Development :: Libraries :: Python Modules
Requires-Python: >=3.9
License-File: LICENSE
License-File: AUTHORS
Requires-Dist: aiohttp>=3.11
Requires-Dist: async-timeout>=4
Requires-Dist: slixmpp>=1.8
Dynamic: license-file
